pymetager/__init__.py
pymetager/cli.py
pymetager/version_manager.py
pymetager-0.0.1.dist-info/LICENSE
pymetager-0.0.1.dist-info/METADATA
pymetager-0.0.1.dist-info/WHEEL
pymetager-0.0.1.dist-info/entry_points.txt
pymetager-0.0.1.dist-info/top_level.txt
pymetager-0.0.1.dist-info/RECORD
