Metadata-Version: 2.1
Name: pymetager
Version: 0.0.1
Summary: A Python package metadata manager by BuildNN.
Home-page: https://github.com/buildnn/pypack-metager
Author: BuildNN Team
Author-email: dev@buildnn.com
Maintainer: BuildNN Team
Maintainer-email: dev@buildnn.com
License: BSD 4-Clause License
Project-URL: Repository, https://github.com/buildnn/pypack-metager
Project-URL: Documentation, https://github.com/buildnn/pypack-metager
Project-URL: Code, https://www.github.com/buildnn/pypack-metager
Project-URL: Issue tracker, https://github.com/buildnn/pypack-metager/issues
Keywords: pypack_metager,buildnn
Platform: UNKNOWN
Classifier: Environment :: Console
Classifier: Intended Audience :: Developers
Classifier: Operating System :: POSIX :: Linux
Classifier: Operating System :: Unix
Classifier: Programming Language :: Python :: 3
Classifier: Topic :: Software Development :: Libraries :: Python Modules
Requires-Python: >=3.8
Requires-Dist: click
Requires-Dist: packaging
